clickhouse_migrate/__init__.py
clickhouse_migrate/migrate.py
clickhouse_migrate/runner.py
clickhouse_migrate/utils.py
chmigrate-0.6.0.dist-info/entry_points.txt
chmigrate-0.6.0.dist-info/WHEEL
chmigrate-0.6.0.dist-info/METADATA
chmigrate-0.6.0.dist-info/RECORD
